g2/__init__.py
g2/chart.py
g2/api/__init__.py
g2/api/chart_for_api.py
g2/api/mark.py
g2/core/__init__.py
g2/core/chart.py
g2/core/engine.py
g2/core/plot.py
g2/core/templates/jupyter-lab.jinja
g2/core/templates/notebook.jinja
g2/core/templates/plot.jinja
g2/external/__init__.py
g2/external/scale.py
g2/spec/__init__.py
g2/spec/animate.py
g2/spec/chart_for_spec.py
g2/spec/component.py
g2/spec/composition.py
g2/spec/encode.py
g2/spec/interaction.py
g2/spec/mark.py
g2/spec/palette.py
g2/spec/scale.py
g2/spec/theme.py
g2/spec/transform.py
g2/spec/utils.py
g2/spec/coordinate/__init__.py
g2/spec/coordinate/coordinate.py
g2/spec/coordinate/coordinate_transform.py
g2/spec/data/__init__.py
g2/spec/data/data.py
g2/spec/data/data_transform.py
g2/spec/label/__init__.py
g2/spec/label/label.py
g2/spec/label/label_transform.py
g2/utils/__init__.py
g2/utils/common.py
g2_examples/__init__.py
g2_examples/api/__init__.py
g2_examples/api/interval.py
g2-2024.6.30.dist-info/LICENSE
g2-2024.6.30.dist-info/METADATA
g2-2024.6.30.dist-info/WHEEL
g2-2024.6.30.dist-info/top_level.txt
g2-2024.6.30.dist-info/RECORD
