Metadata-Version: 2.1
Name: g2
Version: 2024.6.30
Summary: Python3 binding for `@AntV/G2` Plotting Library .
Author-email: "Max, Lin" <jason.m.lin@outlook.com>
License: Apache 2.0
Project-URL: Homepage, https://github.com/Jasonsey/pyG2
Project-URL: Source, https://github.com/Jasonsey/pyG2
Project-URL: Tracker, https://github.com/Jasonsey/pyG2/issues
Classifier: Development Status :: 4 - Beta
Classifier: Environment :: Console
Classifier: Intended Audience :: Developers
Classifier: License :: OSI Approved :: Apache Software License
Classifier: Operating System :: OS Independent
Classifier: Programming Language :: Python
Classifier: Programming Language :: Python :: 3
Classifier: Programming Language :: Python :: 3 :: Only
Classifier: Programming Language :: Python :: 3.10
Classifier: Programming Language :: Python :: 3.11
Classifier: Programming Language :: Python :: 3.12
Classifier: Topic :: Scientific/Engineering
Classifier: Topic :: Software Development
Classifier: Topic :: Software Development :: Libraries
Classifier: Topic :: Software Development :: Libraries :: Python Modules
Requires-Python: >=3.10
License-File: LICENSE
Requires-Dist: simplejson
Requires-Dist: jinja2
